forester/__init__.py
forester/cli.py
forester/folder_contributions.py
forester/tree_info.py
forester/util.py
forester-0.5.2.dist-info/LICENSE
forester-0.5.2.dist-info/METADATA
forester-0.5.2.dist-info/WHEEL
forester-0.5.2.dist-info/entry_points.txt
forester-0.5.2.dist-info/top_level.txt
forester-0.5.2.dist-info/RECORD
