Metadata-Version: 2.1
Name: forester
Version: 0.5.2
Summary: Shell scripts for nursing a linux machine
Home-page: https://github.com/chr1st1ank/forester
Author: chr1st1ank
Author-email: chr1st1ank@pferdeplan.de
License: MIT
Platform: UNKNOWN
Classifier: Development Status :: 4 - Beta
Classifier: License :: OSI Approved :: MIT License
Classifier: Programming Language :: Python
Classifier: Programming Language :: Python :: 3
Classifier: Programming Language :: Python :: 3.6
Classifier: Programming Language :: Python :: 3.7
Classifier: Programming Language :: Python :: 3.8
